8ksram.v
// `timescale 1ns/1ps

// module sram_8kb(input wire clk,
//                 input wire we,
//                 input wire oe,
//                 input wire [10:0] addr,
//                 input wire [31:0] data_in,
//                 output reg [31:0] data_out
//                );

// reg [31:0] mem [0:2047]; // 8KB memory

// always @(posedge clk) begin
//     if(we) begin
//         mem[addr] <= data_in;
//     end
//     else if(oe) begin
//         data_out <= #1 mem[addr];
//     end
//     else begin
//         data_out <= #1 32'bz;
//     end
// end

// endmodule

module sram_8kb #(
    parameter ADDR_WIDTH = 11,
    parameter DATA_WIDTH = 32
)(
    input clk,
    input rd_en,
    input [ADDR_WIDTH-1:0]rd_addr,
    output reg [DATA_WIDTH-1:0]rd_data,

    input wr_en,
    input [ADDR_WIDTH-1:0]wr_addr,
    input [DATA_WIDTH-1:0]wr_data
);

    reg [DATA_WIDTH-1:0] mem [0:(1<<ADDR_WIDTH)-1];

    /* Write */
    always @(posedge clk) begin
        if (wr_en)
            mem[wr_addr] <= wr_data;
    end

    /* Read  */
    always @(*) begin
        if (rd_en)
            rd_data <= mem[rd_addr];
    end

endmodule

ccm_controller.v
`timescale 1ns/1ps

module ccm_controller #(
    parameter ADDR_WIDTH = 11,   // 2048 words
    parameter DATA_WIDTH = 32
)(
    input clk,
    input rst_n,

    input cntlr_rd,
    input [ADDR_WIDTH-1:0] cntlr_raddr,
    output [DATA_WIDTH-1:0] cntlr_rd_data,
    output reg cntlr_rd_valid,

    input cntlr_wr,
    input [ADDR_WIDTH-1:0]cntlr_waddr,
    input [DATA_WIDTH-1:0]cntlr_wr_data,

    //2 port sram 
    
    output  mem_rd,
    output [ADDR_WIDTH-1:0]mem_rd_addr,
    input [DATA_WIDTH-1:0]mem_rd_data,

    output  mem_wr,
    output  [ADDR_WIDTH-1:0]mem_wr_addr,
    output  [DATA_WIDTH-1:0]mem_wr_data
);

     /* -----------------------------
              Write path
       ----------------------------- */
        assign  mem_wr = cntlr_wr;
        assign  mem_wr_addr = cntlr_waddr;
        assign  mem_wr_data = cntlr_wr_data;


    
    /* -------------------------------------------------------
                          Read Path
        - Read data from memory comes back with 1 clock delay
       ------------------------------------------------------- */
    
    
    assign mem_rd = cntlr_rd;
    assign mem_rd_addr = cntlr_raddr;
    assign cntlr_rd_data = mem_rd_data;
    
    
    
    always @(posedge clk) begin
        cntlr_rd_valid <= cntlr_rd; 
    end

endmodule

pc.v

`timescale 1ns/1ps

module pc_block (
    input wire clk,
    input wire rst_n,
    input wire pc_en,
    input wire [1:0] pc_sel,
    input wire [10:0] imm_addr,
    input wire [10:0] alu_addr,
    output reg [10:0] pc
);
    wire [10:0] pc_plus4;
    reg [10:0] pc_next;
    wire [10:0] hold;
    assign hold = pc;

    assign pc_plus4 = pc + 11'd4;

    always @(*) begin
    case (pc_sel)
        2'b00: pc_next = pc_plus4;
        2'b01: pc_next = imm_addr;
        2'b10: pc_next = alu_addr;
        2'b11: pc_next = hold;
        default: pc_next = pc_plus4;
    endcase
    end
    always @(posedge clk or negedge rst_n) 
    begin
        if (!rst_n)
        pc <= 11'd0;
        else if (pc_en)
        pc <= pc_next;
    end

endmodule

fetch_int.v
`timescale 1ns/1ps

module fetch_int #(
    parameter ADDR_WIDTH = 11,   // 2048 words
    parameter DATA_WIDTH = 32
)(
    input clk,
    input rst_n,
    
    input [1:0] pc_sel,
    input [ADDR_WIDTH-1:0] alu_addr,
    input [ADDR_WIDTH-1:0] imm_addr,
    
    input   cntlr_rd,
    output  [DATA_WIDTH-1:0]cntlr_rd_data,
    output  cntlr_rd_valid,

    input cntlr_wr,
    input [ADDR_WIDTH-1:0]cntlr_waddr,
    input [DATA_WIDTH-1:0]cntlr_wr_data,

    output   mem_rd,
    output  [ADDR_WIDTH-1:0]mem_rd_addr,
    input   [DATA_WIDTH-1:0]mem_rd_data,

    output   mem_wr,
    output  [ADDR_WIDTH-1:0]mem_wr_addr,
    output  [DATA_WIDTH-1:0]mem_wr_data
);

    wire [ADDR_WIDTH-1:0] cntlr_raddr;

    //instantiate pc_module & ccm_controller

    pc_block pc_uut (
        .clk(clk), 
        .rst_n(rst_n),
        .pc_en(1'b1),
        .pc_sel(pc_sel),
        .imm_addr(imm_addr),
        .alu_addr(alu_addr),
        .pc(cntlr_raddr)
    );

    ccm_controller ccm_uut (
        .clk(clk),
        .rst_n(rst_n),

        .cntlr_rd(cntlr_rd),
        .cntlr_raddr(cntlr_raddr), // address coming from pc
        .cntlr_rd_data(cntlr_rd_data),
        .cntlr_rd_valid(cntlr_rd_valid),

        .cntlr_wr(cntlr_wr),
        .cntlr_waddr(cntlr_waddr),
        .cntlr_wr_data(cntlr_wr_data),

        .mem_rd(mem_rd),
        .mem_rd_addr(mem_rd_addr),
        .mem_rd_data(mem_rd_data),

        .mem_wr(mem_wr),
        .mem_wr_addr(mem_wr_addr),
        .mem_wr_data(mem_wr_data)
    );


    


endmodule

fetch.v
`timescale 1ns/1ps

module fetch #(
    parameter ADDR_WIDTH = 11,   // 2048 words
    parameter DATA_WIDTH = 32
)(
    input clk,
    input rst_n,

    input [1:0] pc_sel,
    input [ADDR_WIDTH-1:0] alu_addr,
    input [ADDR_WIDTH-1:0] imm_addr,
    
    input cntlr_rd,
    output [DATA_WIDTH-1:0] cntlr_rd_data,
    output  cntlr_rd_valid,

    input cntlr_wr,
    input [ADDR_WIDTH-1:0]cntlr_waddr,
    input [DATA_WIDTH-1:0]cntlr_wr_data

    /* 
    output reg mem_rd,
    output reg [ADDR_WIDTH-1:0]mem_rd_addr,
    input [DATA_WIDTH-1:0]mem_rd_data,

    output reg mem_wr,
    output reg [ADDR_WIDTH-1:0]mem_wr_addr,
    output reg [DATA_WIDTH-1:0]mem_wr_data

    */
);

    wire mem_rd;
    wire [ADDR_WIDTH-1:0]mem_rd_addr;
    wire[DATA_WIDTH-1:0]mem_rd_data;

    wire mem_wr;
    wire [ADDR_WIDTH-1:0]mem_wr_addr;
    wire [DATA_WIDTH-1:0]mem_wr_data;


    //instantiate fetch_int & block ram

    fetch_int uut_1(
        .clk(clk),
        .rst_n(rst_n),

        .pc_sel(pc_sel),
        .imm_addr(imm_addr),
        .alu_addr(alu_addr),

        .cntlr_rd(cntlr_rd),
        .cntlr_rd_data(cntlr_rd_data),
        .cntlr_rd_valid(cntlr_rd_valid),

        .cntlr_wr(cntlr_wr),
        .cntlr_waddr(cntlr_waddr),
        .cntlr_wr_data(cntlr_wr_data),

        .mem_rd(mem_rd),
        .mem_rd_addr(mem_rd_addr),
        .mem_rd_data(mem_rd_data),

        .mem_wr(mem_wr),
        .mem_wr_addr(mem_wr_addr),
        .mem_wr_data(mem_wr_data)
    );

    sram_8kb sram (
        .clk(clk),
        .rd_en(mem_rd),
        .rd_addr(mem_rd_addr),
        .rd_data(mem_rd_data),
        .wr_en(mem_wr),
        .wr_addr(mem_wr_addr),
        .wr_data(mem_wr_data)
    );
    
    


endmodule

fetch_top.v
`timescale 1ns/1ps

module fetch_top();
    parameter ADDR_WIDTH = 11;   // 2048 words
    parameter DATA_WIDTH = 32;

    reg clk;
    reg rst_n;

    reg [1:0] pc_sel;
    reg [ADDR_WIDTH-1:0] alu_addr;
    reg [ADDR_WIDTH-1:0] imm_addr;
    
    reg cntlr_rd;
    wire [DATA_WIDTH-1:0] cntlr_rd_data;
    wire cntlr_rd_valid;

    reg cntlr_wr;
    reg [ADDR_WIDTH-1:0]cntlr_waddr;
    reg [DATA_WIDTH-1:0]cntlr_wr_data;

    

    fetch #(
        .ADDR_WIDTH(ADDR_WIDTH),
        .DATA_WIDTH(DATA_WIDTH)
    ) fetch_inst (
        .clk(clk),
        .rst_n(rst_n),

        .pc_sel(pc_sel),
        .alu_addr(alu_addr),
        .imm_addr(imm_addr),
    
        .cntlr_rd(cntlr_rd),
        .cntlr_rd_data(cntlr_rd_data),
        .cntlr_rd_valid(cntlr_rd_valid),
        .cntlr_wr(cntlr_wr),
        .cntlr_waddr(cntlr_waddr),
        .cntlr_wr_data(cntlr_wr_data)
        );



    always #5 clk = ~clk;

    initial begin
        $dumpfile("fetch_top.vcd"); 
        $dumpvars (0, fetch_top);

        // Initialize signals
        clk = 0;
        rst_n = 0;
        pc_sel = 2'b00;
        alu_addr = 11'b0;
        imm_addr = 11'b0;
        cntlr_rd = 0;
        cntlr_wr = 0;
        cntlr_waddr = 11'b0;
        cntlr_wr_data = 32'b0;

        // Release reset
        #15;
        rst_n = 1;

        // =====================================================
        // TEST SEQUENCES
        // =====================================================

        // -----------------------------
        // 1) Controller Write Sequence
        // -----------------------------
        $display("\n==== TEST 1: CONTROLLER WRITES ====");

        @(negedge clk);
        cntlr_wr = 1;
        cntlr_waddr = 11'd5;
        cntlr_wr_data = 32'hA5A5_0001;
        @(negedge clk);
        cntlr_wr = 0;

        @(negedge clk);
        cntlr_wr = 1;
        cntlr_waddr = 11'd6;
        cntlr_wr_data = 32'hA5A5_0002;
        @(negedge clk);
        cntlr_wr = 0;

        @(negedge clk);
        cntlr_wr = 1;
        cntlr_waddr = 11'd7;
        cntlr_wr_data = 32'hA5A5_0003;
        @(negedge clk);
        cntlr_wr = 0;

        // -----------------------------
        // 2) Controller Read Sequence
        // -----------------------------
        

        @(negedge clk);
        cntlr_rd = 1;
        @(negedge clk);
        cntlr_rd = 0;

        // Wait for valid read data
        wait(cntlr_rd_valid == 1);


        // -----------------------------
        // 3) PC based fetch (pc_sel=0)
        // -----------------------------
        $display("\n==== TEST 3: PC BASED FETCH ====");

        pc_sel = 2'b00;   // PC mode
        // let PC increment and fetch some cycles
        repeat(5) @(negedge clk);

        // -----------------------------
        // 4) ALU based fetch (pc_sel=1)
        // -----------------------------
        $display("\n==== TEST 4: ALU BASED FETCH ====");

        pc_sel = 2'b01;
        imm_addr = 11'd5;  // should fetch 32'hA5A5_0001
         
        @(negedge clk);
        cntlr_rd = 1;
        @(negedge clk);
        cntlr_rd = 0;

        pc_sel = 2'b01;
        imm_addr = 11'd6;

        @(negedge clk);
        cntlr_rd = 1;
        @(negedge clk);
        cntlr_rd = 0;

        pc_sel = 2'b01;
        imm_addr = 11'd6;

        @(negedge clk);
        cntlr_rd = 1;
        @(negedge clk);
        cntlr_rd = 0;

        pc_sel = 2'b01;
        imm_addr = 11'd7;

        @(negedge clk);
        cntlr_rd = 1;
        @(negedge clk);
        cntlr_rd = 0;

        


        // Finish
        #50;
        $display("\n==== ALL TESTS DONE ====");
        $finish;
    end

endmodule

iccm.sim/sim_1/behav/xsim/fetch_top.vcd
$date
   Thu Feb 12 19:03:45 2026
$end

$version
  2024.2.0
  $dumpfile ("fetch_top.vcd") 
$end

$timescale
  1ps
$end

$scope module fetch_top $end
$var reg 1 ! clk $end
$var reg 1 " rst_n $end
$var reg 2 # pc_sel [1:0] $end
$var reg 11 $ alu_addr [10:0] $end
$var reg 11 % imm_addr [10:0] $end
$var reg 1 & cntlr_rd $end
$var wire 32 ' cntlr_rd_data [31:0] $end
$var wire 1 ( cntlr_rd_valid $end
$var reg 1 ) cntlr_wr $end
$var reg 11 * cntlr_waddr [10:0] $end
$var reg 32 + cntlr_wr_data [31:0] $end
$scope module fetch_inst $end
$var wire 1 , clk $end
$var wire 1 - rst_n $end
$var wire 2 . pc_sel [1:0] $end
$var wire 11 / alu_addr [10:0] $end
$var wire 11 0 imm_addr [10:0] $end
$var wire 1 1 cntlr_rd $end
$var wire 32 ' cntlr_rd_data [31:0] $end
$var wire 1 ( cntlr_rd_valid $end
$var wire 1 2 cntlr_wr $end
$var wire 11 3 cntlr_waddr [10:0] $end
$var wire 32 4 cntlr_wr_data [31:0] $end
$var wire 1 5 mem_rd $end
$var wire 11 6 mem_rd_addr [10:0] $end
$var wire 32 7 mem_rd_data [31:0] $end
$var wire 1 8 mem_wr $end
$var wire 11 9 mem_wr_addr [10:0] $end
$var wire 32 : mem_wr_data [31:0] $end
$scope module uut_1 $end
$var wire 1 , clk $end
$var wire 1 - rst_n $end
$var wire 2 . pc_sel [1:0] $end
$var wire 11 / alu_addr [10:0] $end
$var wire 11 0 imm_addr [10:0] $end
$var wire 1 1 cntlr_rd $end
$var wire 32 ' cntlr_rd_data [31:0] $end
$var wire 1 ( cntlr_rd_valid $end
$var wire 1 2 cntlr_wr $end
$var wire 11 3 cntlr_waddr [10:0] $end
$var wire 32 4 cntlr_wr_data [31:0] $end
$var wire 1 5 mem_rd $end
$var wire 11 6 mem_rd_addr [10:0] $end
$var wire 32 7 mem_rd_data [31:0] $end
$var wire 1 8 mem_wr $end
$var wire 11 9 mem_wr_addr [10:0] $end
$var wire 32 : mem_wr_data [31:0] $end
$var wire 11 ; cntlr_raddr [10:0] $end
$scope module pc_uut $end
$var wire 1 , clk $end
$var wire 1 - rst_n $end
$var wire 1 < pc_en $end
$var wire 2 . pc_sel [1:0] $end
$var wire 11 0 imm_addr [10:0] $end
$var wire 11 / alu_addr [10:0] $end
$var reg 11 = pc [10:0] $end
$var wire 11 > pc_plus4 [10:0] $end
$var reg 11 ? pc_next [10:0] $end
$var wire 11 @ hold [10:0] $end
$upscope $end
$scope module ccm_uut $end
$var wire 1 , clk $end
$var wire 1 - rst_n $end
$var wire 1 1 cntlr_rd $end
$var wire 11 ; cntlr_raddr [10:0] $end
$var reg 32 A cntlr_rd_data [31:0] $end
$var reg 1 B cntlr_rd_valid $end
$var wire 1 2 cntlr_wr $end
$var wire 11 3 cntlr_waddr [10:0] $end
$var wire 32 4 cntlr_wr_data [31:0] $end
$var reg 1 C mem_rd $end
$var reg 11 D mem_rd_addr [10:0] $end
$var wire 32 7 mem_rd_data [31:0] $end
$var reg 1 E mem_wr $end
$var reg 11 F mem_wr_addr [10:0] $end
$var reg 32 G mem_wr_data [31:0] $end
$upscope $end
$upscope $end
$scope module sram $end
$var wire 1 , clk $end
$var wire 1 5 rd_en $end
$var wire 11 6 rd_addr [10:0] $end
$var reg 32 H rd_data [31:0] $end
$var wire 1 8 wr_en $end
$var wire 11 9 wr_addr [10:0] $end
$var wire 32 : wr_data [31:0] $end
$upscope $end
$upscope $end
$upscope $end
$enddefinitions $end

#0
$dumpvars
0!
0"
b0 #
b0 $
b0 %
0&
bx '
x(
0)
b0 *
b0 +
0,
0-
b0 .
b0 /
b0 0
01
02
b0 3
b0 4
05
b0 6
bx 7
08
b0 9
b0 :
b0 ;
1<
b0 =
b100 >
b100 ?
b0 @
bx A
xB
0C
b0 D
0E
b0 F
b0 G
bx H
$end

#5000
1!
0(
1,
0B

#10000
0!
0,

#15000
1!
1"
1,
1-
b100 6
b100 ;
b100 =
b1000 >
b1000 ?
b100 @
b100 D

#20000
0!
1)
b101 *
b10100101101001010000000000000001 +
0,
12
b101 3
b10100101101001010000000000000001 4

#25000
1!
1,
b1000 6
18
b101 9
b10100101101001010000000000000001 :
b1000 ;
b1000 =
b1100 >
b1100 ?
b1000 @
b1000 D
1E
b101 F
b10100101101001010000000000000001 G

#30000
0!
0)
0,
02

#35000
1!
1,
b1100 6
08
b1100 ;
b1100 =
b10000 >
b10000 ?
b1100 @
b1100 D
0E

#40000
0!
1)
b110 *
b10100101101001010000000000000010 +
0,
12
b110 3
b10100101101001010000000000000010 4

#45000
1!
1,
b10000 6
18
b110 9
b10100101101001010000000000000010 :
b10000 ;
b10000 =
b10100 >
b10100 ?
b10000 @
b10000 D
1E
b110 F
b10100101101001010000000000000010 G

#50000
0!
0)
0,
02

#55000
1!
1,
b10100 6
08
b10100 ;
b10100 =
b11000 >
b11000 ?
b10100 @
b10100 D
0E

#60000
0!
1)
b111 *
b10100101101001010000000000000011 +
0,
12
b111 3
b10100101101001010000000000000011 4

#65000
1!
1,
b11000 6
18
b111 9
b10100101101001010000000000000011 :
b11000 ;
b11000 =
b11100 >
b11100 ?
b11000 @
b11000 D
1E
b111 F
b10100101101001010000000000000011 G

#70000
0!
0)
0,
02

#75000
1!
1,
b11100 6
08
b11100 ;
b11100 =
b100000 >
b100000 ?
b11100 @
b11100 D
0E

#80000
0!
1&
0,
11
15
1C

#85000
1!
1(
1,
b100000 6
b100000 ;
b100000 =
b100100 >
b100100 ?
b100000 @
1B
b100000 D

#90000
0!
0&
0,
01
05
0C

#95000
1!
0(
1,
b100100 6
b100100 ;
b100100 =
b101000 >
b101000 ?
b100100 @
0B
b100100 D

#100000
0!
0,

#105000
1!
1,
b101000 6
b101000 ;
b101000 =
b101100 >
b101100 ?
b101000 @
b101000 D

#110000
0!
0,

#115000
1!
1,
b101100 6
b101100 ;
b101100 =
b110000 >
b110000 ?
b101100 @
b101100 D

#120000
0!
0,

#125000
1!
1,
b110000 6
b110000 ;
b110000 =
b110100 >
b110100 ?
b110000 @
b110000 D

#130000
0!
0,

#135000
1!
1,
b110100 6
b110100 ;
b110100 =
b111000 >
b111000 ?
b110100 @
b110100 D

#140000
0!
b1 #
b101 %
0,
b1 .
b101 0
b101 ?

#145000
1!
1,
b101 6
b101 ;
b101 =
b1001 >
b101 @
b101 D

#150000
0!
1&
b10100101101001010000000000000001 '
0,
11
15
b10100101101001010000000000000001 7
b10100101101001010000000000000001 A
1C
b10100101101001010000000000000001 H

#155000
1!
1(
1,
1B

#160000
0!
b110 %
0&
0,
b110 0
01
05
b110 ?
0C

#165000
1!
0(
1,
b110 6
b110 ;
b110 =
b1010 >
b110 @
0B
b110 D

#170000
0!
1&
b10100101101001010000000000000010 '
0,
11
15
b10100101101001010000000000000010 7
b10100101101001010000000000000010 A
1C
b10100101101001010000000000000010 H

#175000
1!
1(
1,
1B

#180000
0!
0&
0,
01
05
0C

#185000
1!
0(
1,
0B

#190000
0!
1&
0,
11
15
1C

#195000
1!
1(
1,
1B

#200000
0!
b111 %
0&
0,
b111 0
01
05
b111 ?
0C

#205000
1!
0(
1,
b111 6
b111 ;
b111 =
b1011 >
b111 @
0B
b111 D

#210000
0!
1&
b10100101101001010000000000000011 '
0,
11
15
b10100101101001010000000000000011 7
b10100101101001010000000000000011 A
1C
b10100101101001010000000000000011 H

#215000
1!
1(
1,
1B

#220000
0!
0&
0,
01
05
0C

#225000
1!
0(
1,
0B

